catimage/__init__.py
catimage/__main__.py
catimage/broken.png
catimage/catimage.py
catimage/program_icon.png
catimage-2024.dist-info/entry_points.txt
catimage-2024.dist-info/LICENSE.md
catimage-2024.dist-info/METADATA
catimage-2024.dist-info/WHEEL
catimage-2024.dist-info/RECORD
