Metadata-Version: 2.1
Name: catimage
Version: 2024
Summary: Use to cat an image to the terminal
Home-page: https://github.com/FredHappyface/Python.CatImage
License: MIT
Author: FredHappyface
Requires-Python: >=3.8,<4.0
Classifier: Development Status :: 5 - Production/Stable
Classifier: Environment :: Console
Classifier: Intended Audience :: Developers
Classifier: Intended Audience :: Education
Classifier: License :: OSI Approved :: MIT License
Classifier: Natural Language :: English
Classifier: Operating System :: OS Independent
Classifier: Programming Language :: Python :: 3
Classifier: Programming Language :: Python :: 3.8
Classifier: Programming Language :: Python :: 3.9
Classifier: Programming Language :: Python :: 3.10
Classifier: Programming Language :: Python :: 3.11
Classifier: Programming Language :: Python :: 3.12
Classifier: Programming Language :: Python :: Implementation :: CPython
Classifier: Topic :: Multimedia :: Graphics
Classifier: Topic :: Software Development :: Libraries :: Python Modules
Classifier: Topic :: Utilities
Provides-Extra: full
Requires-Dist: Pillow (>=10.2.0,<11)
Requires-Dist: cli2gui (>=2023,<2025) ; extra == "full"
Project-URL: Documentation, https://github.com/FredHappyface/Python.CatImage/blob/master/README.md
Project-URL: Repository, https://github.com/FredHappyface/Python.CatImage
